GH_CoRE/__init__.py
GH_CoRE/data_dict_settings.py
GH_CoRE/model/Attribute_getter.py
GH_CoRE/model/Attribute_model.py
GH_CoRE/model/ER_config.py
GH_CoRE/model/ER_config_parser.py
GH_CoRE/model/Entity_model.py
GH_CoRE/model/Entity_recognition.py
GH_CoRE/model/Entity_search.py
GH_CoRE/model/Event_model.py
GH_CoRE/model/Relation_extraction.py
GH_CoRE/model/Relation_model.py
GH_CoRE/model/__init__.py
GH_CoRE/model/tst_case.py
GH_CoRE/utils/__init__.py
GH_CoRE/utils/cache.py
GH_CoRE/utils/check_type.py
GH_CoRE/utils/conndb.py
GH_CoRE/utils/prepare_sql.py
GH_CoRE/utils/request_api.py
GH_CoRE/utils/logUtils/__init__.py
GH_CoRE/utils/logUtils/loadLogConfig.py
GH_CoRE/working_flow/__init__.py
GH_CoRE/working_flow/body_content_preprocessing.py
GH_CoRE/working_flow/df_sum_series_values.py
GH_CoRE/working_flow/identify_reference.py
GH_CoRE/working_flow/query_OSDB_github_log.py
GH_CoRE-2.2.4.dist-info/LICENSE
GH_CoRE-2.2.4.dist-info/METADATA
GH_CoRE-2.2.4.dist-info/WHEEL
GH_CoRE-2.2.4.dist-info/top_level.txt
GH_CoRE-2.2.4.dist-info/RECORD
