Metadata-Version: 2.1
Name: GH_CoRE
Version: 2.2.4
Summary: GitHub Collaboration Relation Extraction
Home-page: https://github.com/birdflyi/GitHub_Collaboration_Relation_Extraction
Author-email: birdflyi <zhlou@stu.ecnu.edu.cn>
License:                                  Apache License
Project-URL: Homepage, https://github.com/birdflyi/GitHub_Collaboration_Relation_Extraction
Project-URL: Repository, https://github.com/birdflyi/GitHub_Collaboration_Relation_Extraction.git
Keywords: Relation Extraction,GitHub event,dataset
Platform: any
Classifier: Development Status :: 3 - Alpha
Classifier: Intended Audience :: Developers
Classifier: Intended Audience :: Science/Research
Classifier: License :: OSI Approved :: Apache Software License
Classifier: Operating System :: OS Independent
Classifier: Programming Language :: Python :: 3
Classifier: Programming Language :: Python :: Implementation :: PyPy
Classifier: Topic :: Scientific/Engineering :: Information Analysis
Requires-Python: >=3.6
License-File: LICENSE
